pirate/__init__.py
pirate/data.py
pirate/local.py
pirate/pirate.py
pirate/print.py
pirate/torrent.py
pirate/data/blacklist.json
pirate/data/categories.json
pirate/data/sorts.json
tests/__init__.py
tests/test_local.py
tests/test_pirate.py
tests/test_print.py
tests/test_torrent.py
tests/test_version.py
tests/util.py
tests/data/blocked.html
tests/data/db.csv
tests/data/debian_iso.json
tests/data/no_hits.json
tests/data/result.json
tests/data/rich.xml
pirate_get-0.4.2.dist-info/LICENSE
pirate_get-0.4.2.dist-info/METADATA
pirate_get-0.4.2.dist-info/WHEEL
pirate_get-0.4.2.dist-info/entry_points.txt
pirate_get-0.4.2.dist-info/top_level.txt
pirate_get-0.4.2.dist-info/RECORD
