Metadata-Version: 2.1
Name: pirate-get
Version: 0.4.2
Summary: A command line interface for The Pirate Bay
Home-page: https://github.com/vikstrous/pirate-get
Author: vikstrous
Author-email: me@viktorstanchev.com
License: AGPL
Keywords: torrent,magnet,download,tpb,client
Platform: UNKNOWN
Classifier: Topic :: Utilities
Classifier: Topic :: Terminals
Classifier: Topic :: System :: Networking
Classifier: Programming Language :: Python :: 3 :: Only
Classifier: Programming Language :: Python :: 3.4
Classifier: License :: OSI Approved :: GNU General Public License (GPL)
License-File: LICENSE
Requires-Dist: colorama (>=0.3.3)
Requires-Dist: veryprettytable (>=0.8.1)
Requires-Dist: pyperclip (>=1.6.2)
